rainbow/__init__.py
rainbow/client.py
rainbow/config.py
rainbow/defaults.py
rainbow/schema.py
rainbow/server.py
rainbow/types.py
rainbow/utils.py
rainbow/backends/__init__.py
rainbow/backends/base.py
rainbow/backends/memory.py
rainbow/jobspec/__init__.py
rainbow/jobspec/converter.py
rainbow/jobspec/jobspec.py
rainbow/protos/__init__.py
rainbow/protos/api_pb2.py
rainbow/protos/api_pb2.pyi
rainbow/protos/api_pb2_grpc.py
rainbow/protos/memory_pb2.py
rainbow/protos/memory_pb2.pyi
rainbow/protos/memory_pb2_grpc.py
rainbow/protos/rainbow_pb2.py
rainbow/protos/rainbow_pb2.pyi
rainbow/protos/rainbow_pb2_grpc.py
rainbow_scheduler-0.0.16.dist-info/METADATA
rainbow_scheduler-0.0.16.dist-info/WHEEL
rainbow_scheduler-0.0.16.dist-info/top_level.txt
rainbow_scheduler-0.0.16.dist-info/RECORD
