Metadata-Version: 2.1
Name: rainbow-scheduler
Version: 0.0.16
Summary: Python gRPC functions for the Rainbow Scheduler
Home-page: https://github.com/converged-computing/rainbow/tree/main/python/v1
Author: Vanessasaurus
Author-email: vsoch@users.noreply.github.com
Maintainer: Vanessasaurus
License: MIT
Keywords: multi-cluster,scheduler
Classifier: Intended Audience :: Science/Research
Classifier: Intended Audience :: Developers
Classifier: License :: OSI Approved :: Apache Software License
Classifier: Programming Language :: C
Classifier: Programming Language :: Python
Classifier: Topic :: Software Development
Classifier: Topic :: Scientific/Engineering
Classifier: Operating System :: Unix
Classifier: Programming Language :: Python :: 3.7
Requires-Dist: grpcio
Requires-Dist: grpcio-tools
Requires-Dist: jsonschema
Requires-Dist: pyyaml
Requires-Dist: jobspec
